xenv/Control.py
xenv/TestEnvOps.py
xenv/TestXMLOps.py
xenv/Variable.py
xenv/__init__.py
xenv/xmlModule.py
xenv/tests/__init__.py
xenv/tests/test_command_line.py
xenv/tests/test_variable.py
xenv-1.0.1.dist-info/LICENSE
xenv-1.0.1.dist-info/METADATA
xenv-1.0.1.dist-info/WHEEL
xenv-1.0.1.dist-info/entry_points.txt
xenv-1.0.1.dist-info/top_level.txt
xenv-1.0.1.dist-info/zip-safe
xenv-1.0.1.dist-info/RECORD
